---
layout: post
title:  "Lambda表达式和JVM字节码"
date:   2019-03-16 22:26:00
categories: Java 
tags: Jdk1.8
---

* content
{:toc}




## 匿名类

匿名类可以同时声明和实例化一个类，因此，它和Lambda表达式一样，也能用于提供函数式接口的实现。由于Lambda表达式提供了函数式接口中抽象方法的实现，这让人感觉似乎在编译过程中让Java编译器直接将Lambda表达式转换为匿名类更直观。不过匿名类有不尽人意的特性，会对应用程序的性能带来负面的影响：

- 编译器会为每一个匿名类生成一个新的.class文件。这些新生成的类文件的文件名通常以ClassName$1这种形式呈现，其中ClassName是匿名类出现的类的名字，紧跟着一个美元符号和一个数字。生成大量的类文件时不利的，因为每个类文件在使用之前都需要加载和验证，这会直接影响应用的启动性能。如果将Lambda表达式转换为匿名类，每个Lambda表达式都会产生一个新的类文件，这是不期望发生的

- 每个新的匿名类都会为类或者接口产生一个新的子类型。如果为了实现一个比较器，使用了大量不同的Lambda表达式，这意味着该比较器会有大量的子类型，这种情况下，JVM的运行时性能调优会变得更加困难

## 字节码

Java的源代码文件会经由Java编译器编译为Java字节码，之后JVM可以咨询这些生成的字节码运行应用。编译时，匿名类和Lambda表达式使用了不同的字节码指令。可以通过如下命令查看任何类文件的字节码和常量池：

```java
javap -c -v ClassName
```

- 以匿名内部类的方式实现一个Function接口：

```java

import java.util.function.Function;

public class InnerClass {
    Function<String, String> function = new Function<String, String>() {
        @Override
        public String apply(String s) {
            return s;

        }
    };
}


```

这种方式下，和Function对应，以匿名内部类形式生成的字节码如下：

```java
 0: aload_0
 1: invokespecial #1                  // Method java/lang/Object."<init>":()V
 4: aload_0
 5: new           #2                  // class tech/dlzp/java/code/lambda/InnerClass$1
 8: dup
 9: aload_0
10: invokespecial #3                  // Method tech/dlzp/java/code/lambda/InnerClass$1."<init>":(Ltech/dlzp/java/code/lambda/InnerClass;)V
13: putfield      #4                  // Field function:Ljava/util/function/Function;
16: return


[ByteCode]  

 0 aload_0
 1 invokespecial #1 <java/lang/Object.<init>>
 4 aload_0
 5 new #2 <tech/dlzp/java/code/lambda/InnerClass$1>
 8 dup
 9 aload_0
10 invokespecial #3 <tech/dlzp/java/code/lambda/InnerClass$1.<init>>
13 putfield #4 <tech/dlzp/java/code/lambda/InnerClass.function>
16 return
```
编译中的细节：

- 通过字节码new 一个InnerClass$1类型的对象被实例化，与此同时，一个指向新创建对象的引用会被压如栈
- dup操作会复制栈上的引用
- 接着这个值被invokespecial指令处理，该指令会初始化对象
- 栈顶现在包含了指向对象的引用，该值通过putfield指令保存到function的字段

InnerClass$1是由编译器为匿名类生成的名字：

```java
class tech.dlzp.java.code.lambda.InnerClass$1 extends java.lang.Object implements java.util.function.Function<java.lang.String, java.lang.String>{
	 final tech.dlzp.java.code.lambda.InnerClass this$0;

  public java.lang.Object apply(java.lang.Object);
    descriptor: (Ljava/lang/Object;)Ljava/lang/Object;
    flags: ACC_PUBLIC, ACC_BRIDGE, ACC_SYNTHETIC
    Code:
      stack=2, locals=2, args_size=2
         0: aload_0
         1: aload_1
         2: checkcast     #3                  // class java/lang/String
         5: invokevirtual #4                  // Method apply:(Ljava/lang/String;)Ljava/lang/String;
         8: areturn
      LineNumberTable:
        line 6: 0
      LocalVariableTable:
        Start  Length  Slot  Name   Signature
            0       9     0  this   Ltech/dlzp/java/code/lambda/InnerClass$1;
}

}

```

## InvokeDynamic

使用Lambda表达式实现的Funcation

```java
public class Lambda {
    Function<String, String> function = str -> str;
}
```

```java
 0: aload_0
 1: invokespecial #1                  // Method java/lang/Object."<init>":()V
 4: aload_0
 5: invokedynamic #2,  0              // InvokeDynamic #0:apply:()Ljava/util/function/Function;
10: putfield      #3                  // Field function:Ljava/util/function/Function;
13: return

```

`InvokeDynamic运行机制: 
Java 7引入了invokedynamic指令，它是一个JVM指令，允许动态语言在run-time时动态绑定。Java 8的Lambda表达式并不是匿名类的语法糖，它不会在编译的时候生成类似于匿名类的xxx$1.class，而是在运行的时候使用invokeDynamic指令。对于一条Lambda表达式在class里边会包含一个invokedynamic命令和一个静态方法。运行时会使用LambdaMetafactory#metafactory做成一个Lambda$1的内部类再调用该函数式接口的实例。在运行时生成class，就是避免class太多影响加载速度，像Stream那样的到处是Lambda`

创建额外的类现在被invokedynamic指令替代。invokedynamic指令最初被JDK7引入，用于支持运行于JVM上的动态类型语言，指向方法调用时，invokedynamic添加了更高层的抽象，使得一部分逻辑可以依据动态语言的特征来决定调用目标，这一指令的典型使用场景如下：

```java
def add(a,b){a+b}
```
这里a和b的类型在编译时都未知，有可能随着运行时发生变化。由于这个原因，JVM首次执行invokedynamic调用时，它会查询一个Bootstrap Methods，该方法实现了依赖语言的逻辑，可以决定选择哪一个方法进行调用。Bootstrap方法返回一个链接调用点(linked call site)。很多情况下，如果add方法使用两个int类型的变量，紧接下来的调用也会使用两个int类型的值。所以，每次调用也没有必要都重新选择调用的方法。调用点自身就包含了一定的逻辑，可以判断在什么情况下需要进行重新链接

Lambda表达式中编译后的invokedynamic指令被用于延迟Labmbda表达式到字节码的转换，最终这一操作被推迟到运行时，换句话说，以这种方式使用invokedynamic，可以`将实现invokedynamic表达式的这部分代码的字节码生成推迟到运行时`：

- Lambda表达式的代码块到字节码的转换由高层的策略变成了纯粹的实现细节。它现在可以动态地改变，或者在未来版本中得到优化、修改，并保持了字节码的后向兼容性

- 没有带来额外的开销，没有额外的字段，也不需要进行静态初始化，而这些如果不使用Lambda，就不会实现

- 对无状态非捕获型Lambda，可以创建一个Lambda对象的实例，对其进行缓存，之后对同一对象的访问都返回同样的内容。(以static final 变量的方式声明某个比较器实例)

- 没有额外的性能开销，因为这些转换都是必须的，并且结果也进行了链接，`仅在Lambda首次被调用时需要转换。其后所有的调用都能直接跳过这一步，直接调用之前链接的实现`

## 代码生成策略

将Lambda表达式的代码体填入到运行时动态创建的静态方法，就完成了Lambda表达式的字节码转换。无状态Lambda在它涵盖的范围内不保持任何状态信息，字节码转换时它是所有Lambda中最简单的一种类型，这种情况下，编译器可以生成一个方法，该方法含有该Lambda表达式同样的签名，所以最终转换的结果从逻辑上看起就像下面这样：

```java
public class Lambda{
	Function<String ,String> function=[dynamic invocatin of lambda$1 ]

	static String lambda$1(String str){
		return str;
	}
}
```

Lambda表达式中包含了final(或者效果上等同于final)的本地变量或者字段的情况会稍微复杂一些:

```java
public class Lambda{
	
	String prefix = "xxx";  //编译器重新进行优化
	Function<String,String> function= str -> prefix+str;

}
```

生成方法的签名不会和Lambda表达式一样，因为它还需要携带参数来传递上下文额外的状态。为实现这一目标，最简单的方式是在Lambda中为每一个需要额外保存的变量预留参数：

```java
public class Lambda{
	
	String prefix = "xxx";  //编译器重新进行优化
	Function<String,String> function=[dynamic invocatin of lambda$1 ]

	static String lambda$1(String str,String  prefix){
		return str-> str+ prefix ;
	}

}

```

更多Lambda表达式转换流程:http://cr.openjdk.java.net/~briangoetz/lambda/lambda-translation.html




